{"name":"build-javascript","namedChunkGroups":{"polyfill":{"name":"polyfill","assets":[{"name":"webpack-runtime-d947210ef50030aea396.js","size":5036},{"name":"polyfill-be141cfbd191bfc81b2b.js","size":85828}],"filteredAssets":0,"assetsSize":90864,"filteredAuxiliaryAssets":2,"auxiliaryAssetsSize":227888},"app":{"name":"app","assets":[{"name":"webpack-runtime-d947210ef50030aea396.js","size":5036},{"name":"styles.debdf10d508b58f314ca.css","size":163433},{"name":"framework-89bf2bc271ce7b2d0d61.js","size":130460},{"name":"app-6ea66fed463c267e6435.js","size":167020}],"filteredAssets":0,"assetsSize":465949,"filteredAuxiliaryAssets":3,"auxiliaryAssetsSize":1051843},"component---src-pages-404-js":{"name":"component---src-pages-404-js","assets":[{"name":"component---src-pages-404-js-4d186d80a9989abe2d5f.js","size":794}],"filteredAssets":0,"assetsSize":794,"filteredAuxiliaryAssets":1,"auxiliaryAssetsSize":1984},"component---src-pages-index-js":{"name":"component---src-pages-index-js","assets":[{"name":"styles.debdf10d508b58f314ca.css","size":163433},{"name":"framework-89bf2bc271ce7b2d0d61.js","size":130460},{"name":"cb1608f2-66df3e51f267a78f0c7b.js","size":1545},{"name":"a9a7754c-465021df3154471f2d65.js","size":467089},{"name":"component---src-pages-index-js-76f113d638f6414dbf55.js","size":71327}],"filteredAssets":0,"assetsSize":833854,"filteredAuxiliaryAssets":7,"auxiliaryAssetsSize":1990337}},"assetsByChunkName":{"polyfill":["webpack-runtime-d947210ef50030aea396.js","polyfill-be141cfbd191bfc81b2b.js"],"app":["webpack-runtime-d947210ef50030aea396.js","styles.debdf10d508b58f314ca.css","framework-89bf2bc271ce7b2d0d61.js","app-6ea66fed463c267e6435.js"],"component---src-pages-404-js":["component---src-pages-404-js-4d186d80a9989abe2d5f.js"],"component---src-pages-index-js":["styles.debdf10d508b58f314ca.css","framework-89bf2bc271ce7b2d0d61.js","cb1608f2-66df3e51f267a78f0c7b.js","a9a7754c-465021df3154471f2d65.js","component---src-pages-index-js-76f113d638f6414dbf55.js"]},"childAssetsByChunkName":{}}